yamlify/__init__.py
yamlify/converter/json_to_xml.py
yamlify/converter/json_to_yaml.py
yamlify/converter/xml_to_json.py
yamlify/converter/xml_to_yaml.py
yamlify/converter/yaml_to_json.py
yamlify/converter/yaml_to_xml.py
yamlify/reader/reader.py
yamlify-1.5.0.dist-info/METADATA
yamlify-1.5.0.dist-info/WHEEL
yamlify-1.5.0.dist-info/licenses/AUTHORS.txt
yamlify-1.5.0.dist-info/licenses/LICENSE
yamlify-1.5.0.dist-info/RECORD
