Metadata-Version: 2.1
Name: yamlify
Version: 1.5.0
Summary: Effortlessly Convert Between Data Formats with YAMLify YAMLify is your one-stop solution for seamless conversion between YAML, JSON, and XML formats.
Project-URL: Homepage, https://github.com/aliftech/YAMLify
Project-URL: Bug Tracker, https://github.com/aliftech/YAMLify/issues
Author-email: Wahyu Krisna Aji <wahyukrisnaaji32@gmail.com>
License-File: AUTHORS.txt
License-File: LICENSE
Classifier: License :: OSI Approved :: MIT License
Classifier: Operating System :: OS Independent
Classifier: Programming Language :: Python :: 3
Requires-Python: >=3.8
